cli/__init__.py
cli/cli_peer.py
cli/peer1.py
cli/peer2.py
core/__init__.py
core/globals.py
core/node.py
core/debug/debugging.py
core/models/__init__.py
core/models/message_model.py
core/models/user_model.py
core/networking/__init__.py
core/networking/discovery_manager.py
core/networking/network_manager.py
core/networking/peer.py
core/networking/peer_connection.py
core/networking/peer_crypto.py
core/networking/peer_events.py
core/networking/peer_manager.py
core/networking/peer_state.py
core/storage/__init__.py
core/storage/credentials_manager.py
core/storage/storage_manager.py
core/storage/user_manager.py
core/utils/listener.py
notepasser_ui/__init__.py
notepasser_ui/chat.py
notepasser_ui/main.py
notepasser_ui/utils.py
notepasser_ui/widgets/__init__.py
notepasser_ui/widgets/elements/__init__.py
notepasser_ui/widgets/elements/no_chat_panel.ui
notepasser_ui/widgets/windows/__init__.py
notepasser_ui/widgets/windows/chat_window.ui
notepasser-0.0.15.dist-info/METADATA
notepasser-0.0.15.dist-info/WHEEL
notepasser-0.0.15.dist-info/entry_points.txt
notepasser-0.0.15.dist-info/top_level.txt
notepasser-0.0.15.dist-info/RECORD
