Metadata-Version: 2.4
Name: notepasser
Version: 0.0.15
Summary: Discover users on the same network and send encrypted messages
Author: AmNotAGoose
Project-URL: Homepage, https://github.com/AmNotAGoose/notepasser
Requires-Python: >=3.13
Requires-Dist: build==1.3.0
Requires-Dist: certifi==2025.10.5
Requires-Dist: cffi==2.0.0
Requires-Dist: charset-normalizer==3.4.4
Requires-Dist: colorama==0.4.6
Requires-Dist: cryptography==46.0.3
Requires-Dist: docutils==0.22.2
Requires-Dist: id==1.5.0
Requires-Dist: idna==3.11
Requires-Dist: iniconfig==2.3.0
Requires-Dist: jaraco.classes==3.4.0
Requires-Dist: jaraco.context==6.0.1
Requires-Dist: jaraco.functools==4.3.0
Requires-Dist: keyring==25.6.0
Requires-Dist: markdown-it-py==4.0.0
Requires-Dist: mdurl==0.1.2
Requires-Dist: more-itertools==10.8.0
Requires-Dist: nh3==0.3.1
Requires-Dist: noiseprotocol==0.3.1
Requires-Dist: packaging==25.0
Requires-Dist: pluggy==1.6.0
Requires-Dist: pycparser==2.23
Requires-Dist: Pygments==2.19.2
Requires-Dist: PyNaCl==1.6.0
Requires-Dist: pyproject_hooks==1.2.0
Requires-Dist: PySide6==6.10.0
Requires-Dist: PySide6_Addons==6.10.0
Requires-Dist: PySide6_Essentials==6.10.0
Requires-Dist: pytest==8.4.2
Requires-Dist: pywin32-ctypes==0.2.3
Requires-Dist: readme_renderer==44.0
Requires-Dist: requests==2.32.5
Requires-Dist: requests-toolbelt==1.0.0
Requires-Dist: rfc3986==2.0.0
Requires-Dist: rich==14.2.0
Requires-Dist: shiboken6==6.10.0
Requires-Dist: twine==6.2.0
Requires-Dist: urllib3==2.5.0
